{
  "appInfo" : {
    "build" : "231.9392.1.2311.11076708",
    "buildDate" : "2023-11-09T16:10:22.141Z[UTC]",
    "productCode" : "AI",
    "generated" : "2024-11-29T00:40:43.0390596Z",
    "os" : "Windows 10.0",
    "runtime" : "JetBrains s.r.o. 17.0.7 17.0.7+0-b2043.56-10550314"
  },
  "runtimeInfo" : {
    "maxMemory" : 2147483648,
    "numberOfProcessors" : 8,
    "maxNumberOfIndexingThreads" : 7,
    "maxSizeOfFileForIntelliSense" : 2560000,
    "maxSizeOfFileForContentLoading" : 20971520
  },
  "projectIndexingHistory" : {
    "projectName" : "week13",
    "times" : {
      "indexingReason" : "On refresh of files in week13",
      "scanningType" : "REFRESH",
      "totalUpdatingTime" : 57652600,
      "indexingTime" : 57297600,
      "contentLoadingVisibleTime" : 1520145,
      "creatingIteratorsTime" : 0,
      "scanFilesTime" : 0,
      "pushPropertiesTime" : 0,
      "indexExtensionsTime" : 0,
      "isAppliedAllValuesSeparately" : true,
      "separateApplyingIndexesVisibleTime" : 6701245,
      "updatingStart" : "2024-11-29T00:40:42.9803563Z",
      "updatingEnd" : "2024-11-29T00:40:43.0382295Z",
      "totalSuspendedTime" : 0,
      "wasInterrupted" : false
    },
    "fileCount" : {
      "numberOfFileProviders" : 1,
      "numberOfScannedFiles" : 9,
      "numberOfFilesIndexedByInfrastructureExtensionsDuringScan" : 0,
      "numberOfFilesScheduledForIndexingAfterScan" : 9,
      "numberOfFilesIndexedByInfrastructureExtensionsDuringIndexingStage" : 0,
      "numberOfFilesIndexedWithLoadingContent" : 8
    },
    "totalStatsPerFileType" : [ {
      "fileType" : "PLAIN_TEXT",
      "partOfTotalProcessingTime" : {
        "part" : 56616400,
        "total" : 108866199
      },
      "partOfTotalContentLoadingTime" : {
        "part" : 802600,
        "total" : 2912898
      },
      "totalNumberOfFiles" : 1,
      "totalFilesSize" : 362267,
      "totalProcessingSpeed" : {
        "totalBytes" : 362267,
        "totalTime" : 56616400
      },
      "biggestContributors" : [ {
        "providerName" : "Refreshed files",
        "numberOfFiles" : 1,
        "totalFilesSize" : 362267,
        "partOfTotalProcessingTimeOfThisFileType" : {
          "part" : 56616400,
          "total" : 56616400
        }
      } ]
    }, {
      "fileType" : "JSON",
      "partOfTotalProcessingTime" : {
        "part" : 47337000,
        "total" : 108866199
      },
      "partOfTotalContentLoadingTime" : {
        "part" : 1156698,
        "total" : 2912898
      },
      "totalNumberOfFiles" : 2,
      "totalFilesSize" : 141708,
      "totalProcessingSpeed" : {
        "totalBytes" : 141708,
        "totalTime" : 47337000
      },
      "biggestContributors" : [ {
        "providerName" : "Refreshed files",
        "numberOfFiles" : 2,
        "totalFilesSize" : 141708,
        "partOfTotalProcessingTimeOfThisFileType" : {
          "part" : 47337000,
          "total" : 47337000
        }
      } ]
    }, {
      "fileType" : "AUTO_DETECTED",
      "partOfTotalProcessingTime" : {
        "part" : 4287900,
        "total" : 108866199
      },
      "partOfTotalContentLoadingTime" : {
        "part" : 903000,
        "total" : 2912898
      },
      "totalNumberOfFiles" : 3,
      "totalFilesSize" : 0,
      "totalProcessingSpeed" : {
        "totalBytes" : 0,
        "totalTime" : 4287900
      },
      "biggestContributors" : [ {
        "providerName" : "Refreshed files",
        "numberOfFiles" : 3,
        "totalFilesSize" : 0,
        "partOfTotalProcessingTimeOfThisFileType" : {
          "part" : 4287900,
          "total" : 4287900
        }
      } ]
    }, {
      "fileType" : "UNKNOWN",
      "partOfTotalProcessingTime" : {
        "part" : 624899,
        "total" : 108866199
      },
      "partOfTotalContentLoadingTime" : {
        "part" : 50600,
        "total" : 2912898
      },
      "totalNumberOfFiles" : 2,
      "totalFilesSize" : 0,
      "totalProcessingSpeed" : {
        "totalBytes" : 0,
        "totalTime" : 624899
      },
      "biggestContributors" : [ {
        "providerName" : "Refreshed files",
        "numberOfFiles" : 2,
        "totalFilesSize" : 0,
        "partOfTotalProcessingTimeOfThisFileType" : {
          "part" : 624899,
          "total" : 624899
        }
      } ]
    } ],
    "totalStatsPerIndexer" : [ {
      "indexId" : "Trigram.Index",
      "partOfTotalIndexingTime" : {
        "part" : 33227902,
        "total" : 57699700
      },
      "totalNumberOfFiles" : 6,
      "totalNumberOfFilesIndexedByExtensions" : 0,
      "totalFilesSize" : 503975,
      "indexValueChangerEvaluationSpeed" : {
        "totalBytes" : 503975,
        "totalTime" : 33227902
      },
      "snapshotInputMappingStats" : {
        "totalRequests" : 0,
        "totalMisses" : 0,
        "totalHits" : 0
      }
    }, {
      "indexId" : "IdIndex",
      "partOfTotalIndexingTime" : {
        "part" : 22078598,
        "total" : 57699700
      },
      "totalNumberOfFiles" : 3,
      "totalNumberOfFilesIndexedByExtensions" : 0,
      "totalFilesSize" : 503975,
      "indexValueChangerEvaluationSpeed" : {
        "totalBytes" : 503975,
        "totalTime" : 22078598
      },
      "snapshotInputMappingStats" : {
        "totalRequests" : 0,
        "totalMisses" : 0,
        "totalHits" : 0
      }
    }, {
      "indexId" : "json.file.root.values",
      "partOfTotalIndexingTime" : {
        "part" : 2393200,
        "total" : 57699700
      },
      "totalNumberOfFiles" : 2,
      "totalNumberOfFilesIndexedByExtensions" : 0,
      "totalFilesSize" : 141708,
      "indexValueChangerEvaluationSpeed" : {
        "totalBytes" : 141708,
        "totalTime" : 2393200
      },
      "snapshotInputMappingStats" : {
        "totalRequests" : 0,
        "totalMisses" : 0,
        "totalHits" : 0
      }
    } ],
    "scanningStatistics" : [ {
      "providerName" : "Refreshed files",
      "numberOfScannedFiles" : 9,
      "numberOfSkippedFiles" : 0,
      "numberOfFilesForIndexing" : 9,
      "numberOfFilesFullyIndexedByInfrastructureExtensions" : 0,
      "filesFullyIndexedByInfrastructureExtensions" : [ ],
      "statusTime" : 0,
      "scanningTime" : 91700,
      "timeProcessingUpToDateFiles" : 0,
      "timeUpdatingContentLessIndexes" : 0,
      "timeIndexingWithoutContent" : 0,
      "roots" : [ "Not collected for refresh" ]
    } ],
    "fileProviderStatistics" : [ {
      "providerName" : "Refreshed files",
      "totalNumberOfIndexedFiles" : 8,
      "totalNumberOfFilesFullyIndexedByExtensions" : 0,
      "totalIndexingVisibleTime" : 56813700,
      "contentLoadingVisibleTime" : 1520145,
      "numberOfTooLargeForIndexingFiles" : 0,
      "slowIndexedFiles" : [ ],
      "filesFullyIndexedByExtensions" : [ ],
      "isAppliedAllValuesSeparately" : true,
      "separateApplyingIndexesVisibleTime" : 6701245
    } ],
    "visibleTimeToAllThreadTimeRatio" : 0.5218672142673044
  }
}